{
    "0": [
        0.0,
        21.5,
        0.0,
        5.0,
        5.0,
        0.0,
        0.0,
        0.0,
        0.0,
        0.0,
        0.0,
        5.0,
        0.0,
        5.0,
        0.0,
        0.0,
        0.0,
        67.0,
        0.0,
        0.0
    ],
    "1": [
        0.0,
        21.5,
        0.0,
        67.5,
        5.0,
        0.0,
        0.0,
        0.0,
        33.5,
        0.0,
        0.0,
        93.0,
        0.0,
        5.0,
        0.0,
        0.0,
        0.0,
        102.5,
        0.0,
        0.0
    ],
    "2": [
        0.0,
        30.25,
        0.0,
        101.75,
        5.0,
        0.0,
        0.0,
        0.0,
        33.5,
        0.0,
        0.0,
        142.0,
        0.0,
        5.0,
        0.0,
        0.0,
        0.0,
        121.75,
        0.0,
        0.0
    ],
    "3": [
        0.0,
        36.125,
        0.0,
        122.375,
        5.0,
        0.0,
        0.0,
        0.0,
        49.75,
        0.0,
        0.0,
        167.0,
        0.0,
        5.0,
        0.0,
        0.0,
        0.0,
        130.875,
        0.0,
        0.0
    ],
    "4": [
        0.0,
        42.5625,
        0.0,
        133.6875,
        5.0,
        0.0,
        0.0,
        0.0,
        57.875,
        0.0,
        0.0,
        187.5,
        0.0,
        5.0,
        0.0,
        0.0,
        0.0,
        136.4375,
        0.0,
        0.0
    ],
    "5": [
        0.0,
        41.78125,
        0.0,
        137.84375,
        5.0,
        0.0,
        0.0,
        0.0,
        58.4375,
        0.0,
        0.0,
        198.25,
        0.0,
        5.0,
        0.0,
        0.0,
        0.0,
        133.71875,
        0.0,
        0.0
    ],
    "6": [
        0.0,
        42.390625,
        0.0,
        138.921875,
        5.0,
        0.0,
        0.0,
        0.0,
        60.21875,
        0.0,
        0.0,
        198.125,
        0.0,
        5.0,
        0.0,
        0.0,
        0.0,
        132.859375,
        0.0,
        0.0
    ],
    "7": [
        0.0,
        43.1953125,
        0.0,
        138.9609375,
        5.0,
        0.0,
        0.0,
        0.0,
        63.109375,
        0.0,
        0.0,
        202.0625,
        0.0,
        5.0,
        0.0,
        0.0,
        0.0,
        126.9296875,
        0.0,
        0.0
    ],
    "8": [
        0.0,
        44.59765625,
        0.0,
        129.48046875,
        5.0,
        0.0,
        0.0,
        0.0,
        63.0546875,
        0.0,
        0.0,
        210.53125,
        0.0,
        5.0,
        0.0,
        0.0,
        0.0,
        120.46484375,
        0.0,
        0.0
    ],
    "9": [
        0.0,
        45.298828125,
        0.0,
        127.740234375,
        5.0,
        0.0,
        0.0,
        0.0,
        63.52734375,
        0.0,
        0.0,
        212.765625,
        0.0,
        5.0,
        0.0,
        0.0,
        0.0,
        116.232421875,
        0.0,
        0.0
    ],
    "10": [
        0.0,
        47.6494140625,
        0.0,
        126.3701171875,
        5.0,
        0.0,
        0.0,
        0.0,
        65.263671875,
        0.0,
        0.0,
        221.8828125,
        0.0,
        5.0,
        0.0,
        0.0,
        0.0,
        112.1162109375,
        0.0,
        0.0
    ],
    "11": [
        0.0,
        46.82470703125,
        0.0,
        122.68505859375,
        5.0,
        0.0,
        0.0,
        0.0,
        68.6318359375,
        0.0,
        0.0,
        231.44140625,
        0.0,
        5.0,
        0.0,
        0.0,
        0.0,
        104.55810546875,
        0.0,
        0.0
    ],
    "12": [
        0.0,
        45.412353515625,
        0.0,
        121.342529296875,
        5.0,
        0.0,
        0.0,
        0.0,
        71.81591796875,
        0.0,
        0.0,
        234.720703125,
        0.0,
        5.0,
        0.0,
        0.0,
        0.0,
        96.779052734375,
        0.0,
        0.0
    ],
    "13": [
        0.0,
        45.7061767578125,
        0.0,
        124.1712646484375,
        5.0,
        0.0,
        0.0,
        0.0,
        77.407958984375,
        0.0,
        0.0,
        242.3603515625,
        0.0,
        5.0,
        0.0,
        0.0,
        0.0,
        94.3895263671875,
        0.0,
        0.0
    ],
    "14": [
        0.0,
        50.35308837890625,
        0.0,
        125.08563232421875,
        5.0,
        0.0,
        0.0,
        0.0,
        83.7039794921875,
        0.0,
        0.0,
        246.18017578125,
        0.0,
        5.0,
        0.0,
        0.0,
        0.0,
        91.19476318359375,
        0.0,
        0.0
    ],
    "15": [
        0.0,
        54.676544189453125,
        0.0,
        126.54281616210938,
        5.0,
        0.0,
        0.0,
        0.0,
        87.85198974609375,
        0.0,
        0.0,
        249.090087890625,
        0.0,
        5.0,
        0.0,
        0.0,
        0.0,
        89.59738159179688,
        0.0,
        0.0
    ],
    "16": [
        0.0,
        54.676544189453125,
        0.0,
        126.77140808105469,
        5.0,
        0.0,
        0.0,
        0.0,
        91.92599487304688,
        0.0,
        0.0,
        251.5450439453125,
        0.0,
        102.0,
        0.0,
        0.0,
        0.0,
        92.29869079589844,
        0.0,
        0.0
    ],
    "17": [
        0.0,
        54.676544189453125,
        0.0,
        124.88570404052734,
        5.0,
        0.0,
        0.0,
        0.0,
        97.46299743652344,
        0.0,
        0.0,
        241.27252197265625,
        0.0,
        150.0,
        0.0,
        0.0,
        0.0,
        92.64934539794922,
        0.0,
        0.0
    ],
    "18": [
        0.0,
        54.676544189453125,
        0.0,
        123.44285202026367,
        5.0,
        0.0,
        0.0,
        0.0,
        97.23149871826172,
        0.0,
        0.0,
        239.13626098632812,
        0.0,
        175.0,
        0.0,
        0.0,
        0.0,
        96.82467269897461,
        0.0,
        0.0
    ],
    "19": [
        0.0,
        54.676544189453125,
        0.0,
        124.22142601013184,
        5.0,
        0.0,
        0.0,
        0.0,
        95.11574935913086,
        0.0,
        0.0,
        247.56813049316406,
        0.0,
        193.5,
        0.0,
        0.0,
        0.0,
        95.9123363494873,
        0.0,
        0.0
    ],
    "20": [
        0.0,
        54.676544189453125,
        0.0,
        128.61071300506592,
        5.0,
        0.0,
        0.0,
        0.0,
        92.05787467956543,
        0.0,
        0.0,
        255.28406524658203,
        0.0,
        203.25,
        0.0,
        0.0,
        0.0,
        90.45616817474365,
        0.0,
        0.0
    ],
    "21": [
        0.0,
        54.676544189453125,
        0.0,
        129.30535650253296,
        5.0,
        0.0,
        0.0,
        0.0,
        92.02893733978271,
        0.0,
        0.0,
        256.642032623291,
        0.0,
        211.125,
        0.0,
        0.0,
        0.0,
        88.22808408737183,
        0.0,
        0.0
    ],
    "22": [
        0.0,
        54.676544189453125,
        0.0,
        131.15267825126648,
        5.0,
        0.0,
        0.0,
        0.0,
        93.51446866989136,
        0.0,
        0.0,
        264.3210163116455,
        0.0,
        208.5625,
        0.0,
        0.0,
        0.0,
        84.11404204368591,
        0.0,
        0.0
    ],
    "23": [
        0.0,
        54.676544189453125,
        0.0,
        131.07633912563324,
        5.0,
        0.0,
        0.0,
        0.0,
        91.75723433494568,
        0.0,
        0.0,
        271.66050815582275,
        0.0,
        205.28125,
        0.0,
        0.0,
        0.0,
        82.05702102184296,
        0.0,
        0.0
    ],
    "24": [
        0.0,
        54.676544189453125,
        0.0,
        130.53816956281662,
        5.0,
        0.0,
        0.0,
        0.0,
        93.37861716747284,
        0.0,
        0.0,
        277.3302540779114,
        0.0,
        206.140625,
        0.0,
        0.0,
        0.0,
        77.52851051092148,
        0.0,
        0.0
    ],
    "25": [
        0.0,
        54.676544189453125,
        0.0,
        134.2690847814083,
        5.0,
        0.0,
        0.0,
        0.0,
        90.18930858373642,
        0.0,
        0.0,
        282.6651270389557,
        0.0,
        206.0703125,
        0.0,
        0.0,
        0.0,
        73.26425525546074,
        0.0,
        0.0
    ],
    "26": [
        0.0,
        49.83827209472656,
        0.0,
        133.13454239070415,
        5.0,
        0.0,
        0.0,
        0.0,
        91.59465429186821,
        0.0,
        0.0,
        271.83256351947784,
        0.0,
        203.03515625,
        0.0,
        0.0,
        0.0,
        73.26425525546074,
        0.0,
        0.0
    ],
    "27": [
        0.0,
        49.83827209472656,
        0.0,
        129.56727119535208,
        5.0,
        0.0,
        0.0,
        0.0,
        91.7973271459341,
        0.0,
        0.0,
        265.4162817597389,
        0.0,
        199.517578125,
        0.0,
        0.0,
        0.0,
        70.63212762773037,
        0.0,
        0.0
    ],
    "28": [
        0.0,
        49.83827209472656,
        0.0,
        129.28363559767604,
        5.0,
        0.0,
        0.0,
        0.0,
        91.39866357296705,
        0.0,
        0.0,
        258.70814087986946,
        0.0,
        200.2587890625,
        0.0,
        0.0,
        0.0,
        67.31606381386518,
        0.0,
        0.0
    ],
    "29": [
        0.0,
        49.83827209472656,
        0.0,
        131.14181779883802,
        5.0,
        0.0,
        0.0,
        0.0,
        91.19933178648353,
        0.0,
        0.0,
        252.35407043993473,
        0.0,
        200.12939453125,
        0.0,
        0.0,
        0.0,
        63.65803190693259,
        0.0,
        0.0
    ],
    "30": [
        0.0,
        49.83827209472656,
        0.0,
        133.070908899419,
        5.0,
        0.0,
        0.0,
        0.0,
        90.59966589324176,
        0.0,
        0.0,
        248.17703521996737,
        0.0,
        197.564697265625,
        0.0,
        0.0,
        0.0,
        60.329015953466296,
        0.0,
        0.0
    ],
    "31": [
        0.0,
        49.83827209472656,
        0.0,
        131.0354544497095,
        5.0,
        0.0,
        0.0,
        0.0,
        88.79983294662088,
        0.0,
        0.0,
        246.08851760998368,
        0.0,
        194.7823486328125,
        0.0,
        0.0,
        0.0,
        57.66450797673315,
        0.0,
        0.0
    ],
    "32": [
        0.0,
        49.83827209472656,
        0.0,
        130.01772722485475,
        5.0,
        0.0,
        0.0,
        0.0,
        85.39991647331044,
        0.0,
        0.0,
        251.54425880499184,
        0.0,
        193.39117431640625,
        0.0,
        0.0,
        0.0,
        57.832253988366574,
        0.0,
        0.0
    ],
    "33": [
        0.0,
        44.91913604736328,
        0.0,
        126.50886361242738,
        5.0,
        0.0,
        0.0,
        0.0,
        83.19995823665522,
        0.0,
        0.0,
        259.7721294024959,
        0.0,
        192.69558715820312,
        0.0,
        0.0,
        0.0,
        57.832253988366574,
        0.0,
        0.0
    ],
    "34": [
        0.0,
        44.91913604736328,
        0.0,
        125.75443180621369,
        5.0,
        0.0,
        0.0,
        0.0,
        84.09997911832761,
        0.0,
        0.0,
        262.88606470124796,
        0.0,
        195.84779357910156,
        0.0,
        0.0,
        0.0,
        54.91612699418329,
        0.0,
        0.0
    ],
    "35": [
        0.0,
        40.45956802368164,
        0.0,
        123.37721590310684,
        5.0,
        0.0,
        0.0,
        0.0,
        85.5499895591638,
        0.0,
        0.0,
        263.943032350624,
        0.0,
        201.42389678955078,
        0.0,
        0.0,
        0.0,
        54.91612699418329,
        0.0,
        0.0
    ],
    "36": [
        0.0,
        40.45956802368164,
        0.0,
        123.18860795155342,
        5.0,
        0.0,
        0.0,
        0.0,
        90.2749947795819,
        0.0,
        0.0,
        264.971516175312,
        0.0,
        211.2119483947754,
        0.0,
        0.0,
        0.0,
        54.45806349709164,
        0.0,
        0.0
    ],
    "37": [
        0.0,
        40.45956802368164,
        0.0,
        120.09430397577671,
        5.0,
        0.0,
        0.0,
        0.0,
        91.63749738979095,
        0.0,
        0.0,
        265.985758087656,
        0.0,
        219.1059741973877,
        0.0,
        0.0,
        0.0,
        49.22903174854582,
        0.0,
        0.0
    ],
    "38": [
        0.0,
        40.45956802368164,
        0.0,
        117.54715198788836,
        5.0,
        0.0,
        0.0,
        0.0,
        88.81874869489548,
        0.0,
        0.0,
        271.492879043828,
        0.0,
        224.55298709869385,
        0.0,
        0.0,
        0.0,
        46.61451587427291,
        0.0,
        0.0
    ],
    "39": [
        0.0,
        34.22978401184082,
        0.0,
        121.27357599394418,
        5.0,
        0.0,
        0.0,
        0.0,
        85.40937434744774,
        0.0,
        0.0,
        272.246439521914,
        0.0,
        232.77649354934692,
        0.0,
        0.0,
        0.0,
        46.61451587427291,
        0.0,
        0.0
    ],
    "40": [
        0.0,
        34.22978401184082,
        0.0,
        121.13678799697209,
        5.0,
        0.0,
        0.0,
        0.0,
        86.20468717372387,
        0.0,
        0.0,
        264.123219760957,
        0.0,
        236.88824677467346,
        0.0,
        0.0,
        0.0,
        49.307257937136455,
        0.0,
        0.0
    ],
    "41": [
        0.0,
        34.22978401184082,
        0.0,
        124.06839399848604,
        5.0,
        0.0,
        0.0,
        0.0,
        87.60234358686193,
        0.0,
        0.0,
        264.0616098804785,
        0.0,
        237.44412338733673,
        0.0,
        0.0,
        0.0,
        51.65362896856823,
        0.0,
        0.0
    ],
    "42": [
        0.0,
        34.22978401184082,
        0.0,
        131.53419699924302,
        5.0,
        0.0,
        0.0,
        0.0,
        86.30117179343097,
        0.0,
        0.0,
        266.03080494023925,
        0.0,
        233.72206169366837,
        0.0,
        0.0,
        0.0,
        52.826814484284114,
        0.0,
        0.0
    ],
    "43": [
        0.0,
        34.22978401184082,
        0.0,
        134.2670984996215,
        5.0,
        0.0,
        0.0,
        0.0,
        85.65058589671548,
        0.0,
        0.0,
        264.5154024701196,
        0.0,
        234.36103084683418,
        0.0,
        0.0,
        0.0,
        52.826814484284114,
        0.0,
        0.0
    ],
    "44": [
        0.0,
        34.22978401184082,
        0.0,
        135.63354924981076,
        5.0,
        0.0,
        0.0,
        0.0,
        78.32529294835774,
        0.0,
        0.0,
        269.2577012350598,
        0.0,
        232.6805154234171,
        0.0,
        0.0,
        0.0,
        49.91340724214206,
        0.0,
        0.0
    ],
    "45": [
        0.0,
        34.22978401184082,
        0.0,
        140.31677462490538,
        5.0,
        0.0,
        0.0,
        0.0,
        72.16264647417887,
        0.0,
        0.0,
        275.6288506175299,
        0.0,
        226.84025771170855,
        0.0,
        0.0,
        0.0,
        49.95670362107103,
        0.0,
        0.0
    ],
    "46": [
        0.0,
        34.22978401184082,
        0.0,
        138.1583873124527,
        5.0,
        0.0,
        0.0,
        0.0,
        72.08132323708944,
        0.0,
        0.0,
        280.81442530876495,
        0.0,
        224.92012885585427,
        0.0,
        0.0,
        0.0,
        49.978351810535514,
        0.0,
        0.0
    ],
    "47": [
        0.0,
        34.22978401184082,
        0.0,
        136.57919365622635,
        5.0,
        0.0,
        0.0,
        0.0,
        72.54066161854472,
        0.0,
        0.0,
        287.4072126543825,
        0.0,
        221.46006442792714,
        0.0,
        0.0,
        0.0,
        48.98917590526776,
        0.0,
        0.0
    ],
    "48": [
        0.0,
        34.22978401184082,
        0.0,
        138.7895968281132,
        5.0,
        0.0,
        0.0,
        0.0,
        70.27033080927237,
        0.0,
        0.0,
        301.2036063271912,
        0.0,
        214.23003221396357,
        0.0,
        0.0,
        0.0,
        43.49458795263388,
        0.0,
        0.0
    ],
    "49": [
        0.0,
        34.22978401184082,
        0.0,
        140.3947984140566,
        5.0,
        0.0,
        0.0,
        0.0,
        69.63516540463618,
        0.0,
        0.0,
        311.6018031635956,
        0.0,
        206.11501610698178,
        0.0,
        0.0,
        0.0,
        40.74729397631694,
        0.0,
        0.0
    ],
    "50": [
        0.0,
        34.22978401184082,
        0.0,
        144.6973992070283,
        5.0,
        0.0,
        0.0,
        0.0,
        69.31758270231809,
        0.0,
        0.0,
        319.8009015817978,
        0.0,
        200.0575080534909,
        0.0,
        0.0,
        0.0,
        39.37364698815847,
        0.0,
        0.0
    ],
    "51": [
        0.0,
        34.22978401184082,
        0.0,
        149.34869960351415,
        5.0,
        0.0,
        0.0,
        0.0,
        69.15879135115904,
        0.0,
        0.0,
        329.9004507908989,
        0.0,
        197.02875402674545,
        0.0,
        0.0,
        0.0,
        40.186823494079235,
        0.0,
        0.0
    ],
    "52": [
        0.0,
        34.22978401184082,
        3.5,
        155.67434980175707,
        5.0,
        0.0,
        0.0,
        0.0,
        66.57939567557952,
        0.0,
        0.0,
        340.4502253954495,
        0.0,
        194.01437701337272,
        0.0,
        0.0,
        0.0,
        40.186823494079235,
        0.0,
        0.0
    ],
    "53": [
        0.0,
        34.22978401184082,
        3.5,
        157.33717490087855,
        5.0,
        0.0,
        0.0,
        0.0,
        66.78969783778976,
        0.0,
        0.0,
        334.72511269772474,
        0.0,
        199.00718850668636,
        0.0,
        0.0,
        0.0,
        40.186823494079235,
        0.0,
        0.0
    ],
    "54": [
        0.0,
        35.11489200592041,
        3.5,
        158.16858745043928,
        5.0,
        0.0,
        0.0,
        0.0,
        65.39484891889488,
        0.0,
        0.0,
        331.36255634886237,
        0.0,
        199.50359425334318,
        0.0,
        0.0,
        0.0,
        40.186823494079235,
        0.0,
        0.0
    ],
    "55": [
        0.0,
        35.11489200592041,
        3.5,
        159.58429372521965,
        5.0,
        0.0,
        0.0,
        0.0,
        64.69742445944743,
        0.0,
        0.0,
        324.6812781744312,
        0.0,
        204.7517971266716,
        0.0,
        0.0,
        0.0,
        41.09341174703962,
        0.0,
        0.0
    ],
    "56": [
        0.0,
        34.557446002960205,
        3.5,
        161.79214686260983,
        5.0,
        0.0,
        0.0,
        0.0,
        64.69742445944743,
        0.0,
        0.0,
        326.8406390872156,
        0.0,
        207.3758985633358,
        0.0,
        0.0,
        0.0,
        43.04670587351981,
        0.0,
        0.0
    ],
    "57": [
        0.0,
        34.557446002960205,
        3.5,
        161.3960734313049,
        5.0,
        0.0,
        0.0,
        0.0,
        64.34871222972372,
        0.0,
        0.0,
        336.4203195436078,
        0.0,
        209.1879492816679,
        0.0,
        0.0,
        0.0,
        46.523352936759906,
        0.0,
        0.0
    ],
    "58": [
        0.0,
        34.557446002960205,
        3.5,
        161.69803671565245,
        5.0,
        0.0,
        0.0,
        0.0,
        65.67435611486187,
        0.0,
        0.0,
        345.7101597718039,
        0.0,
        209.09397464083395,
        0.0,
        0.0,
        0.0,
        45.76167646837995,
        0.0,
        0.0
    ],
    "59": [
        0.0,
        34.557446002960205,
        3.5,
        161.84901835782622,
        5.0,
        0.0,
        0.0,
        0.0,
        68.33717805743093,
        0.0,
        0.0,
        354.35507988590194,
        0.0,
        202.54698732041697,
        0.0,
        0.0,
        0.0,
        45.38083823418998,
        0.0,
        0.0
    ],
    "60": [
        0.0,
        37.7787230014801,
        3.5,
        160.92450917891313,
        5.0,
        0.0,
        0.0,
        0.0,
        68.33717805743093,
        0.0,
        0.0,
        350.67753994295094,
        0.0,
        198.7734936602085,
        0.0,
        0.0,
        0.0,
        43.69041911709499,
        0.0,
        0.0
    ],
    "61": [
        0.0,
        37.7787230014801,
        3.5,
        159.96225458945656,
        5.0,
        0.0,
        0.0,
        0.0,
        69.16858902871547,
        0.0,
        0.0,
        346.3387699714755,
        0.0,
        197.88674683010424,
        0.0,
        0.0,
        0.0,
        41.845209558547495,
        0.0,
        0.0
    ],
    "62": [
        0.0,
        37.7787230014801,
        3.5,
        160.98112729472828,
        5.0,
        0.0,
        0.0,
        0.0,
        66.58429451435774,
        0.0,
        0.0,
        334.16938498573774,
        0.0,
        199.44337341505212,
        0.0,
        0.0,
        0.0,
        39.42260477927375,
        0.0,
        0.0
    ],
    "63": [
        0.0,
        31.38936150074005,
        3.5,
        159.99056364736413,
        5.0,
        0.0,
        0.0,
        0.0,
        62.79214725717887,
        0.0,
        0.0,
        329.58469249286884,
        0.0,
        197.72168670752606,
        0.0,
        0.0,
        0.0,
        39.42260477927375,
        0.0,
        0.0
    ],
    "64": [
        0.0,
        31.38936150074005,
        3.5,
        161.99528182368206,
        5.0,
        0.0,
        0.0,
        0.0,
        62.396073628589434,
        0.0,
        0.0,
        332.7923462464344,
        0.0,
        195.86084335376302,
        0.0,
        0.0,
        0.0,
        37.71130238963687,
        0.0,
        0.0
    ],
    "65": [
        0.0,
        31.38936150074005,
        3.5,
        160.49764091184102,
        5.0,
        0.0,
        0.0,
        0.0,
        60.69803681429472,
        0.0,
        0.0,
        327.8961731232172,
        0.0,
        191.9304216768815,
        0.0,
        0.0,
        0.0,
        36.855651194818435,
        0.0,
        0.0
    ],
    "66": [
        0.0,
        31.38936150074005,
        3.5,
        162.2488204559205,
        5.0,
        0.0,
        0.0,
        0.0,
        62.349018407147355,
        0.0,
        0.0,
        335.9480865616086,
        0.0,
        189.46521083844075,
        0.0,
        0.0,
        0.0,
        33.92782559740922,
        0.0,
        0.0
    ],
    "67": [
        0.0,
        35.194680750370026,
        3.5,
        165.62441022796025,
        5.0,
        0.0,
        0.0,
        0.0,
        60.67450920357368,
        0.0,
        0.0,
        336.97404328080427,
        0.0,
        180.73260541922036,
        0.0,
        0.0,
        0.0,
        33.92782559740922,
        0.0,
        0.0
    ],
    "68": [
        0.0,
        38.09734037518501,
        3.5,
        168.31220511398013,
        5.0,
        0.0,
        0.0,
        0.0,
        59.33725460178684,
        0.0,
        0.0,
        352.98702164040213,
        0.0,
        176.36630270961018,
        0.0,
        0.0,
        0.0,
        33.92782559740922,
        0.0,
        0.0
    ],
    "69": [
        0.0,
        40.548670187592506,
        3.5,
        166.15610255699005,
        5.0,
        0.0,
        0.0,
        0.0,
        59.66862730089342,
        0.0,
        0.0,
        355.9935108202011,
        0.0,
        185.1831513548051,
        0.0,
        0.0,
        0.0,
        33.92782559740922,
        0.0,
        0.0
    ],
    "70": [
        0.0,
        43.77433509379625,
        3.5,
        161.07805127849502,
        5.0,
        0.0,
        0.0,
        0.0,
        59.83431365044671,
        0.0,
        0.0,
        353.99675541010055,
        0.0,
        194.59157567740255,
        0.0,
        0.0,
        0.0,
        33.92782559740922,
        0.0,
        0.0
    ],
    "71": [
        0.0,
        47.38716754689813,
        3.5,
        159.5390256392475,
        5.0,
        0.0,
        0.0,
        0.0,
        59.91715682522336,
        0.0,
        0.0,
        347.4983777050503,
        0.0,
        201.29578783870127,
        0.0,
        0.0,
        0.0,
        33.92782559740922,
        0.0,
        0.0
    ],
    "72": [
        0.0,
        47.38716754689813,
        3.5,
        157.76951281962374,
        5.0,
        0.0,
        0.0,
        0.0,
        57.45857841261168,
        6.0,
        0.0,
        343.24918885252515,
        0.0,
        210.64789391935062,
        0.0,
        0.0,
        0.0,
        33.92782559740922,
        0.0,
        0.0
    ],
    "73": [
        0.0,
        49.69358377344906,
        3.5,
        154.88475640981187,
        5.0,
        0.0,
        0.0,
        0.0,
        53.729289206305836,
        6.0,
        0.0,
        333.12459442626255,
        0.0,
        218.8239469596753,
        0.0,
        0.0,
        0.0,
        33.92782559740922,
        0.0,
        0.0
    ],
    "74": [
        0.0,
        50.84679188672453,
        3.5,
        151.44237820490594,
        5.0,
        0.0,
        0.0,
        0.0,
        55.36464460315292,
        6.0,
        0.0,
        319.0622972131313,
        0.0,
        218.41197347983766,
        0.0,
        0.0,
        0.0,
        33.92782559740922,
        0.0,
        0.0
    ],
    "75": [
        0.0,
        50.84679188672453,
        3.5,
        153.72118910245297,
        5.0,
        0.0,
        0.0,
        0.0,
        57.68232230157646,
        6.0,
        0.0,
        307.03114860656564,
        0.0,
        217.20598673991884,
        0.0,
        0.0,
        0.0,
        33.92782559740922,
        0.0,
        28.5
    ],
    "76": [
        0.0,
        53.923395943362266,
        3.5,
        153.36059455122648,
        5.0,
        0.0,
        0.0,
        0.0,
        62.84116115078823,
        6.0,
        0.0,
        303.01557430328285,
        0.0,
        217.10299336995942,
        0.0,
        0.0,
        0.0,
        33.92782559740922,
        0.0,
        28.5
    ],
    "77": [
        0.0,
        52.96169797168113,
        3.5,
        156.18029727561324,
        5.0,
        0.0,
        0.0,
        0.0,
        61.92058057539411,
        6.0,
        0.0,
        305.5077871516414,
        0.0,
        220.05149668497972,
        0.0,
        0.0,
        0.0,
        33.92782559740922,
        0.0,
        28.5
    ],
    "78": [
        0.0,
        52.96169797168113,
        3.5,
        151.59014863780664,
        5.0,
        0.0,
        0.0,
        0.0,
        57.460290287697056,
        6.0,
        0.0,
        304.2538935758207,
        0.0,
        221.02574834248986,
        0.0,
        0.0,
        0.0,
        32.96391279870461,
        0.0,
        28.5
    ],
    "79": [
        0.0,
        49.48084898584057,
        3.5,
        147.29507431890332,
        5.0,
        0.0,
        0.0,
        0.0,
        53.73014514384853,
        6.0,
        0.0,
        304.62694678791036,
        0.0,
        225.51287417124493,
        0.0,
        0.0,
        0.0,
        32.96391279870461,
        0.0,
        28.5
    ],
    "80": [
        0.0,
        44.24042449292028,
        3.5,
        142.14753715945164,
        5.0,
        0.0,
        0.0,
        0.0,
        52.365072571924266,
        6.0,
        0.0,
        302.8134733939552,
        0.0,
        232.25643708562245,
        0.0,
        0.0,
        0.0,
        32.96391279870461,
        0.0,
        28.5
    ],
    "81": [
        0.0,
        42.62021224646014,
        3.5,
        147.57376857972582,
        5.0,
        0.0,
        0.0,
        0.0,
        54.68253628596213,
        6.0,
        0.0,
        299.9067366969776,
        0.0,
        235.12821854281123,
        0.0,
        0.0,
        0.0,
        32.96391279870461,
        0.0,
        28.5
    ],
    "82": [
        0.0,
        41.81010612323007,
        3.5,
        152.7868842898629,
        5.0,
        0.0,
        0.0,
        0.0,
        58.341268142981065,
        6.0,
        0.0,
        301.45336834848877,
        0.0,
        244.5641092714056,
        0.0,
        0.0,
        0.0,
        32.96391279870461,
        0.0,
        28.5
    ],
    "83": [
        0.0,
        41.81010612323007,
        3.5,
        153.89344214493144,
        5.0,
        0.0,
        0.0,
        0.0,
        62.17063407149053,
        6.0,
        0.0,
        306.7266841742444,
        0.0,
        260.2820546357028,
        0.0,
        0.0,
        0.0,
        29.481956399352306,
        0.0,
        28.5
    ],
    "84": [
        0.0,
        43.405053061615035,
        3.5,
        157.94672107246572,
        5.0,
        0.0,
        0.0,
        0.0,
        63.58531703574526,
        6.0,
        0.0,
        319.8633420871222,
        0.0,
        267.6410273178514,
        0.0,
        0.0,
        0.0,
        29.481956399352306,
        0.0,
        28.5
    ],
    "85": [
        0.0,
        43.405053061615035,
        3.5,
        157.97336053623286,
        5.0,
        0.0,
        0.0,
        0.0,
        66.29265851787264,
        6.0,
        0.0,
        318.9316710435611,
        0.0,
        271.32051365892573,
        0.0,
        0.0,
        0.0,
        27.240978199676153,
        0.0,
        28.5
    ],
    "86": [
        0.0,
        39.70252653080752,
        3.5,
        161.98668026811643,
        5.0,
        0.0,
        0.0,
        0.0,
        71.64632925893632,
        6.0,
        0.0,
        315.96583552178055,
        0.0,
        276.16025682946287,
        0.0,
        0.0,
        0.0,
        27.240978199676153,
        0.0,
        28.5
    ],
    "87": [
        0.0,
        39.70252653080752,
        3.5,
        165.4933401340582,
        63.0,
        0.0,
        0.0,
        0.0,
        71.32316462946815,
        6.0,
        0.0,
        325.48291776089025,
        0.0,
        273.08012841473146,
        0.0,
        0.0,
        0.0,
        27.240978199676153,
        0.0,
        28.5
    ],
    "88": [
        0.0,
        39.70252653080752,
        3.5,
        164.7466700670291,
        89.0,
        0.0,
        0.0,
        0.0,
        69.66158231473408,
        6.0,
        0.0,
        336.2414588804451,
        0.0,
        264.54006420736573,
        0.0,
        0.0,
        0.0,
        27.240978199676153,
        0.0,
        28.5
    ],
    "89": [
        0.0,
        39.70252653080752,
        3.5,
        161.87333503351454,
        101.0,
        0.0,
        0.0,
        0.0,
        71.33079115736703,
        6.0,
        0.0,
        342.6207294402226,
        0.0,
        257.77003210368287,
        0.0,
        0.0,
        0.0,
        27.240978199676153,
        0.0,
        28.5
    ],
    "90": [
        0.0,
        39.70252653080752,
        3.5,
        160.43666751675727,
        111.0,
        0.0,
        0.0,
        0.0,
        72.16539557868352,
        6.0,
        0.0,
        348.8103647201113,
        0.0,
        255.38501605184143,
        0.0,
        0.0,
        0.0,
        27.240978199676153,
        0.0,
        28.5
    ],
    "91": [
        0.0,
        39.70252653080752,
        3.5,
        159.71833375837863,
        112.5,
        0.0,
        0.0,
        0.0,
        75.08269778934175,
        6.0,
        0.0,
        358.4051823600556,
        0.0,
        259.1925080259207,
        0.0,
        0.0,
        0.0,
        27.240978199676153,
        0.0,
        28.5
    ],
    "92": [
        0.0,
        39.70252653080752,
        3.5,
        157.85916687918933,
        109.25,
        0.0,
        0.0,
        0.0,
        76.04134889467088,
        6.0,
        0.0,
        373.2025911800278,
        0.0,
        261.59625401296034,
        0.0,
        0.0,
        0.0,
        27.240978199676153,
        0.0,
        28.5
    ],
    "93": [
        0.0,
        39.70252653080752,
        3.5,
        157.42958343959467,
        108.625,
        0.0,
        0.0,
        0.0,
        75.02067444733544,
        6.0,
        0.0,
        369.60129559001393,
        0.0,
        257.2981270064802,
        0.0,
        0.0,
        0.0,
        27.240978199676153,
        0.0,
        28.5
    ],
    "94": [
        0.0,
        39.70252653080752,
        3.5,
        150.71479171979735,
        110.3125,
        0.0,
        0.0,
        0.0,
        75.51033722366772,
        6.0,
        0.0,
        380.80064779500697,
        0.0,
        251.6490635032401,
        0.0,
        0.0,
        0.0,
        27.240978199676153,
        0.0,
        28.5
    ],
    "95": [
        0.0,
        39.70252653080752,
        3.5,
        151.85739585989867,
        117.65625,
        0.0,
        0.0,
        0.0,
        72.25516861183385,
        6.0,
        0.0,
        389.9003238975035,
        0.0,
        250.82453175162004,
        0.0,
        0.0,
        0.0,
        27.240978199676153,
        0.0,
        28.5
    ],
    "96": [
        0.0,
        39.70252653080752,
        3.5,
        150.92869792994935,
        120.328125,
        0.0,
        0.0,
        0.0,
        65.12758430591693,
        6.0,
        0.0,
        395.95016194875177,
        0.0,
        252.91226587581002,
        0.0,
        0.0,
        0.0,
        27.240978199676153,
        0.0,
        28.5
    ],
    "97": [
        0.0,
        39.70252653080752,
        3.5,
        151.96434896497468,
        123.1640625,
        0.0,
        0.0,
        0.0,
        60.06379215295846,
        6.0,
        0.0,
        386.9750809743759,
        0.0,
        247.456132937905,
        0.0,
        0.0,
        0.0,
        27.240978199676153,
        0.0,
        28.5
    ],
    "98": [
        0.0,
        39.70252653080752,
        3.5,
        152.98217448248732,
        123.58203125,
        0.0,
        0.0,
        0.0,
        57.53189607647923,
        6.0,
        0.0,
        380.48754048718797,
        0.0,
        260.22806646895253,
        0.0,
        0.0,
        0.0,
        27.240978199676153,
        0.0,
        28.5
    ]
}